hatcher/__init__.py
hatcher/__main__.py
hatcher/_version.py
hatcher/api.py
hatcher/errors.py
hatcher/testing.py
hatcher/utils.py
hatcher/cli/__init__.py
hatcher/cli/common.py
hatcher/cli/exporter.py
hatcher/cli/importer.py
hatcher/cli/main.py
hatcher/cli/organization_actions.py
hatcher/cli/repository_actions.py
hatcher/cli/server_actions.py
hatcher/cli/user_actions.py
hatcher/cli/utils.py
hatcher/cli/tests/__init__.py
hatcher/cli/tests/test_utils.py
hatcher/cli/v0/__init__.py
hatcher/cli/v0/repository_actions.py
hatcher/cli/v0/tests/__init__.py
hatcher/cli/v0/tests/test_api_tokens_commands.py
hatcher/cli/v0/tests/test_egg_commands.py
hatcher/cli/v0/tests/test_exporter.py
hatcher/cli/v0/tests/test_main.py
hatcher/cli/v0/tests/test_organization_commands.py
hatcher/cli/v0/tests/test_runtime_commands.py
hatcher/cli/v0/tests/test_user_commands.py
hatcher/cli/v1/__init__.py
hatcher/cli/v1/repository_actions.py
hatcher/cli/v1/tests/__init__.py
hatcher/cli/v1/tests/test_bundle_actions.py
hatcher/cli/v1/tests/test_exporter.py
hatcher/cli/v1/tests/test_importer.py
hatcher/cli/v1/tests/test_runtime_commands.py
hatcher/core/__init__.py
hatcher/core/auth.py
hatcher/core/brood_client.py
hatcher/core/brood_url_handler.py
hatcher/core/model_registry.py
hatcher/core/organization.py
hatcher/core/repository.py
hatcher/core/url_templates.py
hatcher/core/user.py
hatcher/core/utils.py
hatcher/core/tests/__init__.py
hatcher/core/tests/base_test_brood_client.py
hatcher/core/tests/common.py
hatcher/core/tests/test_json_schema_test_mixin.py
hatcher/core/tests/test_url_builder.py
hatcher/core/tests/test_url_handler.py
hatcher/core/tests/test_utils.py
hatcher/core/tests/v0/__init__.py
hatcher/core/tests/v0/base_test_organization.py
hatcher/core/tests/v0/base_test_repository.py
hatcher/core/tests/v0/base_test_user.py
hatcher/core/tests/v0/brood_client_responses.py
hatcher/core/tests/v0/test_brood_client.py
hatcher/core/tests/v1/__init__.py
hatcher/core/tests/v1/base_test_organization.py
hatcher-0.17.0.dist-info/LICENSE.txt
hatcher-0.17.0.dist-info/METADATA
hatcher-0.17.0.dist-info/WHEEL
hatcher-0.17.0.dist-info/entry_points.txt
hatcher-0.17.0.dist-info/top_level.txt
hatcher-0.17.0.dist-info/RECORD
