Metadata-Version: 2.1
Name: hatcher
Version: 0.17.0
Author: Enthought Inc.
Author-email: info@enthought.com
License: BSD
Classifier: Development Status :: 4 - Beta
Classifier: Intended Audience :: Developers
Classifier: License :: OSI Approved :: BSD License
Classifier: Operating System :: OS Independent
Classifier: Programming Language :: Python :: 3.8
Requires-Python: >=3.8
License-File: LICENSE.txt
Requires-Dist: requests (!=2.5.1,<3.0,>=2.4.0)
Requires-Dist: okonomiyaki[all] (>=2.0.0)
Requires-Dist: click (>=8.0)
Requires-Dist: six (>=1.10.0)
Requires-Dist: pyyaml (>=3.11)
Requires-Dist: tabulate (>=0.7)
Requires-Dist: pytz (>=2016.10)
Requires-Dist: tzlocal (>=1.3)
